[
  {
    "domain": "nestle.com",
    "analyzed_at": "2025-12-30T22:26:37.495451",
    "accessible": false,
    "health_hazards": {},
    "behavioral_hazards": {},
    "marketing_tactics": {},
    "promoted_products": [],
    "related_domains": [],
    "risk_score": 0,
    "justification": [],
    "error": "403 Client Error: Forbidden for url: https://www.nestle.com/"
  },
  {
    "domain": "nestle.ca",
    "analyzed_at": "2025-12-30T22:26:40.036651",
    "accessible": false,
    "health_hazards": {},
    "behavioral_hazards": {},
    "marketing_tactics": {},
    "promoted_products": [],
    "related_domains": [],
    "risk_score": 0,
    "justification": [],
    "error": "403 Client Error: Forbidden for url: https://www.madewithnestle.ca/"
  },
  {
    "domain": "nestle.co.uk",
    "analyzed_at": "2025-12-30T22:26:42.790855",
    "accessible": false,
    "health_hazards": {},
    "behavioral_hazards": {},
    "marketing_tactics": {},
    "promoted_products": [],
    "related_domains": [],
    "risk_score": 0,
    "justification": [],
    "error": "403 Client Error: Forbidden for url: https://www.nestle.co.uk"
  },
  {
    "domain": "nespresso.com",
    "analyzed_at": "2025-12-30T22:26:45.292963",
    "accessible": true,
    "health_hazards": {},
    "behavioral_hazards": {},
    "marketing_tactics": {},
    "promoted_products": [],
    "related_domains": [],
    "risk_score": 0,
    "justification": [],
    "seo_metadata": ""
  },
  {
    "domain": "gerber.com",
    "analyzed_at": "2025-12-30T22:26:47.752565",
    "accessible": false,
    "health_hazards": {},
    "behavioral_hazards": {},
    "marketing_tactics": {},
    "promoted_products": [],
    "related_domains": [],
    "risk_score": 0,
    "justification": [],
    "error": "403 Client Error: Forbidden for url: https://www.gerber.com"
  },
  {
    "domain": "purina.com",
    "analyzed_at": "2025-12-30T22:31:31.622838",
    "accessible": false,
    "health_hazards": {},
    "behavioral_hazards": {},
    "marketing_tactics": {},
    "promoted_products": [],
    "related_domains": [],
    "risk_score": 0,
    "justification": [],
    "error": "403 Client Error: Forbidden for url: https://www.purina.com/"
  },
  {
    "domain": "gerber.ai",
    "analyzed_at": "2025-12-30T22:31:34.154073",
    "accessible": false,
    "health_hazards": {},
    "behavioral_hazards": {},
    "marketing_tactics": {},
    "promoted_products": [],
    "related_domains": [],
    "risk_score": 0,
    "justification": [],
    "error": "HTTPSConnectionPool(host='gerber.ai', port=443): Max retries exceeded with url: / (Caused by SSLError(SSLError(1, '[SSL: TLSV1_ALERT_INTERNAL_ERROR] tlsv1 alert internal error (_ssl.c:1016)')))"
  },
  {
    "domain": "gerber.app",
    "analyzed_at": "2025-12-30T22:31:36.407640",
    "accessible": false,
    "health_hazards": {},
    "behavioral_hazards": {},
    "marketing_tactics": {},
    "promoted_products": [],
    "related_domains": [],
    "risk_score": 0,
    "justification": [],
    "error": "HTTPSConnectionPool(host='gerber.app', port=443): Max retries exceeded with url: / (Caused by SSLError(SSLCertVerificationError(1, \"[SSL: CERTIFICATE_VERIFY_FAILED] certificate verify failed: Hostname mismatch, certificate is not valid for 'gerber.app'. (_ssl.c:1016)\")))"
  },
  {
    "domain": "gerber.biz",
    "analyzed_at": "2025-12-30T22:31:38.533866",
    "accessible": false,
    "health_hazards": {},
    "behavioral_hazards": {},
    "marketing_tactics": {},
    "promoted_products": [],
    "related_domains": [],
    "risk_score": 0,
    "justification": [],
    "error": "Insufficient content (possible bot detection or JS-rendered page)"
  },
  {
    "domain": "gerber.ca",
    "analyzed_at": "2025-12-30T22:31:40.941893",
    "accessible": true,
    "health_hazards": {},
    "behavioral_hazards": {},
    "marketing_tactics": {},
    "promoted_products": [],
    "related_domains": [],
    "risk_score": 0,
    "justification": [],
    "seo_metadata": ""
  },
  {
    "domain": "gerber.co.uk",
    "analyzed_at": "2025-12-30T22:45:58.193125",
    "accessible": false,
    "health_hazards": {},
    "behavioral_hazards": {},
    "marketing_tactics": {},
    "promoted_products": [],
    "related_domains": [],
    "risk_score": 0,
    "justification": [],
    "error": "403 Client Error: Forbidden for url: https://gerber.co.uk/"
  },
  {
    "domain": "gerber.dev",
    "analyzed_at": "2025-12-30T22:46:00.331658",
    "accessible": true,
    "health_hazards": {},
    "behavioral_hazards": {},
    "marketing_tactics": {},
    "promoted_products": [],
    "related_domains": [],
    "risk_score": 0,
    "justification": [],
    "seo_metadata": ""
  },
  {
    "domain": "gerber.info",
    "analyzed_at": "2025-12-30T22:46:02.510931",
    "accessible": false,
    "health_hazards": {},
    "behavioral_hazards": {},
    "marketing_tactics": {},
    "promoted_products": [],
    "related_domains": [],
    "risk_score": 0,
    "justification": [],
    "error": "HTTPSConnectionPool(host='gerber.info', port=443): Max retries exceeded with url: / (Caused by ConnectTimeoutError(<HTTPSConnection(host='gerber.info', port=443) at 0x7663813043d0>, 'Connection to gerber.info timed out. (connect timeout=10)'))"
  },
  {
    "domain": "gerber.io",
    "analyzed_at": "2025-12-30T22:46:14.541124",
    "accessible": false,
    "health_hazards": {},
    "behavioral_hazards": {},
    "marketing_tactics": {},
    "promoted_products": [],
    "related_domains": [],
    "risk_score": 0,
    "justification": [],
    "error": "HTTPSConnectionPool(host='gerber.io', port=443): Max retries exceeded with url: / (Caused by ConnectTimeoutError(<HTTPSConnection(host='gerber.io', port=443) at 0x766381305e90>, 'Connection to gerber.io timed out. (connect timeout=10)'))"
  },
  {
    "domain": "gerber.net",
    "analyzed_at": "2025-12-30T22:46:26.587131",
    "accessible": false,
    "health_hazards": {},
    "behavioral_hazards": {},
    "marketing_tactics": {},
    "promoted_products": [],
    "related_domains": [],
    "risk_score": 0,
    "justification": [],
    "error": "HTTPSConnectionPool(host='gerber.net', port=443): Max retries exceeded with url: / (Caused by SSLError(SSLCertVerificationError(1, \"[SSL: CERTIFICATE_VERIFY_FAILED] certificate verify failed: Hostname mismatch, certificate is not valid for 'gerber.net'. (_ssl.c:1016)\")))"
  }
]